cloudhub_client/__init__.py
cloudhub_client/api_client.py
cloudhub_client/configuration.py
cloudhub_client/rest.py
cloudhub_client/api/__init__.py
cloudhub_client/api/sessions_api.py
cloudhub_client/models/__init__.py
cloudhub_client/models/certificate_model.py
cloudhub_client/models/session_create_request.py
cloudhub_client/models/session_model.py
cloudhub_client/models/sign_hash_request.py
cloudhub_client/models/trust_service_auth_parameters_model.py
cloudhub_client/models/trust_service_info_model.py
cloudhub_client/models/trust_service_session_types.py
test/__init__.py
test/test_certificate_model.py
test/test_session_create_request.py
test/test_session_model.py
test/test_sessions_api.py
test/test_sign_hash_request.py
test/test_trust_service_auth_parameters_model.py
test/test_trust_service_info_model.py
test/test_trust_service_session_types.py
cloudhub_client-1.0.1.dist-info/METADATA
cloudhub_client-1.0.1.dist-info/WHEEL
cloudhub_client-1.0.1.dist-info/top_level.txt
cloudhub_client-1.0.1.dist-info/RECORD
