Metadata-Version: 2.1
Name: cloudhub-client
Version: 1.0.1
Summary: Cloudhub API
Home-page: 
Author-email: 
Keywords: Swagger,Cloudhub API
Requires-Dist: urllib3 >=1.15
Requires-Dist: six >=1.10
Requires-Dist: certifi
Requires-Dist: python-dateutil
